selenium_crawler_template/__init__.py
selenium_crawler_template-0.4.0.dist-info/METADATA
selenium_crawler_template-0.4.0.dist-info/WHEEL
selenium_crawler_template-0.4.0.dist-info/top_level.txt
selenium_crawler_template-0.4.0.dist-info/RECORD
