Metadata-Version: 2.1
Name: selenium-crawler-template
Version: 0.4.0
Summary: Boilerplate for developing crawler with Selenium.
Home-page: https://github.com/yeongbin-jo/python-selenium-crawler-template
Author: Yeongbin Jo
Author-email: yeongbin.jo@pylab.co
License: MIT
Keywords: chromedriver chrome selenium splinter
Platform: UNKNOWN
Classifier: Development Status :: 5 - Production/Stable
Classifier: Topic :: Software Development :: Testing
Classifier: Topic :: System :: Installation/Setup
Classifier: Topic :: Software Development :: Libraries :: Python Modules
Classifier: License :: OSI Approved :: MIT License
Classifier: Programming Language :: Python :: 3
Classifier: Programming Language :: Python :: 3.6
Classifier: Programming Language :: Python :: 3.7
Classifier: Programming Language :: Python :: 3.8
Requires-Python: >=3
